{
  "custom_types": {
    "GHAppInstallation": {
      "icon": {
        "type": "font-awesome",
        "name": "window-restore",
        "color": "#EFC41D"
      }
    },
    "GHBranch": {
      "icon": {
        "type": "font-awesome",
        "name": "code-branch",
        "color": "#FF80D2"
      }
    },
    "GHOrganization": {
      "icon": {
        "type": "font-awesome",
        "name": "building",
        "color": "#5FED83"
      }
    },
    "GHOrgRole": {
      "icon": {
        "type": "font-awesome",
        "name": "user-tie",
        "color": "#BFFFD1"
      }
    },
    "GHRepository": {
      "icon": {
        "type": "font-awesome",
        "name": "box-archive",
        "color": "#9EECFF"
      }
    },
    "GHRepoRole": {
      "icon": {
        "type": "font-awesome",
        "name": "user-tie",
        "color": "#DEFEFA"
      }
    },
    "GHSecretScanningAlert": {
      "icon": {
        "type": "font-awesome",
        "name": "key",
        "color": "#3C7A6E"
      }
    },
    "GHTeam": {
      "icon": {
        "type": "font-awesome",
        "name": "user-group",
        "color": "#C06EFF"
      }
    },
    "GHTeamRole": {
      "icon": {
        "type": "font-awesome",
        "name": "user-tie",
        "color": "#D0B0FF"
      }
    },
    "GHUser": {
      "icon": {
        "type": "font-awesome",
        "name": "user",
        "color": "#FF8E40"
      }
    }
  }
}
